wa_analyzer/__init__.py
wa_analyzer/humanhasher.py
wa_analyzer/model.py
wa_analyzer/pathtest.py
wa_analyzer/preprocess.py
wa_analyzer/settings.py
wa_analyzer-0.4.1.dist-info/METADATA
wa_analyzer-0.4.1.dist-info/WHEEL
wa_analyzer-0.4.1.dist-info/entry_points.txt
wa_analyzer-0.4.1.dist-info/RECORD
