Metadata-Version: 2.3
Name: wa-analyzer
Version: 0.4.1
Summary: Code for the Master of Applied Data Science course Data Analysis and Visualization
Project-URL: GitHub, https://github.com/raoulg/MADS-DAV
Author-email: Raoul Grouls <Raoul.Grouls@han.nl>
License: MIT
Requires-Python: <3.12,>=3.11
Requires-Dist: click>=8.1.7
Requires-Dist: loguru>=0.7.2
Requires-Dist: numpy>=1.26.3
Requires-Dist: pandas>=2.2.0
Requires-Dist: pyarrow>=15.0.0
Requires-Dist: pydantic>=2.5.3
Requires-Dist: scikit-learn>=1.4.0
Requires-Dist: seaborn>=0.13.1
Requires-Dist: statsmodels>=0.14.1
Provides-Extra: huggingface
Requires-Dist: sentence-transformers>=2.5.1; extra == 'huggingface'
Requires-Dist: torch>=2.2.1; extra == 'huggingface'
Requires-Dist: transformers>=4.38.2; extra == 'huggingface'
Provides-Extra: plotting
Requires-Dist: mads-datasets>=0.3.14; extra == 'plotting'
Requires-Dist: plotly>=5.18.0; extra == 'plotting'
Requires-Dist: streamlit>=1.31.1; extra == 'plotting'
